{"version":1,"resource":"vscode-remote://ssh-remote%2B133.242.159.244/home/miura/google.py","entries":[{"id":"sbsp.py","timestamp":1660033489120},{"id":"zVF8.py","timestamp":1660033572299},{"id":"7FLq.py","timestamp":1660033725783},{"id":"Yj5X.py","timestamp":1660033781239},{"id":"tEAz.py","timestamp":1660033872731},{"id":"vFCz.py","timestamp":1660034040578},{"id":"Rttq.py","timestamp":1660034070054},{"id":"xZWB.py","timestamp":1660034092122},{"id":"48mh.py","timestamp":1660034280058},{"id":"bxjk.py","timestamp":1660034299110},{"id":"O2jQ.py","timestamp":1660034566085},{"id":"yR8r.py","timestamp":1660034631649},{"id":"U7EL.py","timestamp":1660034677621},{"id":"H4DG.py","timestamp":1660034760321},{"id":"G4H3.py","timestamp":1660035738446},{"id":"vDaa.py","timestamp":1660036074621},{"id":"b8FO.py","timestamp":1660523598435},{"id":"1wgw.py","source":"undoRedo.source","timestamp":1660524187637},{"id":"DMYI.py","timestamp":1660524550573},{"id":"Xs1N.py","timestamp":1660524682037},{"id":"7Egs.py","timestamp":1660524754552},{"id":"ZFC0.py","timestamp":1660524812340},{"id":"w5qW.py","timestamp":1660524827072},{"id":"lnnD.py","timestamp":1660524858640},{"id":"UMbV.py","timestamp":1660527068515},{"id":"mwCJ.py","timestamp":1660527127307},{"id":"688J.py","source":"undoRedo.source","timestamp":1660527288067},{"id":"cFrx.py","timestamp":1660527374478},{"id":"YeOY.py","timestamp":1660527424366},{"id":"9SWr.py","timestamp":1660527471290},{"id":"gDm6.py","timestamp":1660527522518},{"id":"q1ne.py","timestamp":1660527780669},{"id":"eoWe.py","timestamp":1660527856441},{"id":"6uTE.py","timestamp":1660527871709},{"id":"PdEt.py","timestamp":1660528168964},{"id":"bpyc.py","source":"undoRedo.source","timestamp":1660528244416},{"id":"hi4l.py","timestamp":1660528288016},{"id":"AaRg.py","timestamp":1660528331140},{"id":"Bjk8.py","timestamp":1660528359948},{"id":"Wkyz.py","timestamp":1660528541679},{"id":"84qg.py","timestamp":1660528646183},{"id":"5eQj.py","timestamp":1660528690263},{"id":"FQPw.py","timestamp":1660528841755},{"id":"Wyyc.py","timestamp":1660531638184},{"id":"tg4v.py","timestamp":1660531665260},{"id":"0YLy.py","source":"undoRedo.source","timestamp":1660531984191},{"id":"Ay8j.py","timestamp":1660532199363},{"id":"Tmbr.py","timestamp":1660532266966},{"id":"gB8b.py","timestamp":1660532314646},{"id":"oCjl.py","timestamp":1661156300837}]}